rbssim2/CrossSection.py
rbssim2/Detector.py
rbssim2/Element.py
rbssim2/Experiment.py
rbssim2/Files.py
rbssim2/Geometry.py
rbssim2/Globals.py
rbssim2/Layer.py
rbssim2/Simulation.py
rbssim2/Stopping.py
rbssim2/_Stopping.py
rbssim2/__init__.py
rbssim2/fortran/Stopping.cpython-310-x86_64-linux-gnu.so
rbssim2/fortran/Stopping.f95
rbssim2/fortran/utilsrbs.cpython-310-x86_64-linux-gnu.so
rbssim2/fortran/utilsrbs.f95
"rbssim2/resources/cross_section/12C(4He,4He)12C_150.r33"
"rbssim2/resources/cross_section/12C(4He,4He)12C_170.r33"
rbssim2/resources/cross_section/150/c26493sc.r33
rbssim2/resources/cross_section/150/c2aa0$104 (1).r33
rbssim2/resources/cross_section/150/c2aa0$27 (1).r33
rbssim2/resources/cross_section/150/c2aa0$49.r33
rbssim2/resources/cross_section/150/c2aa0$81.r33
rbssim2/resources/cross_section/150/c2aa0_b (1).r33
rbssim2/resources/cross_section/150/c2aa0p.r33
rbssim2/resources/cross_section/150/c2aa0s (1).r33
"rbssim2/resources/cross_section/16O(4He,4He)16O_150.r33"
"rbssim2/resources/cross_section/16O(4He,4He)16O_170.r33"
rbssim2/resources/cross_section/170/c26217sc.r33
rbssim2/resources/cross_section/170/c2aa0$71.r33
rbssim2/resources/cross_section/170/c2aa0_i (1).r33
rbssim2/resources/cross_section/170/c2aa0m.r33
rbssim2/resources/cross_section/170/c2aa0o (2).r33
rbssim2/resources/stop/1_1_26.dat
rbssim2/resources/stop/1_1_28.dat
rbssim2/resources/stop/1_1_42.dat
rbssim2/resources/stop/2_4_1.dat
rbssim2/resources/stop/2_4_11.dat
rbssim2/resources/stop/2_4_12.dat
rbssim2/resources/stop/2_4_13.dat
rbssim2/resources/stop/2_4_14.dat
rbssim2/resources/stop/2_4_14_.dat
rbssim2/resources/stop/2_4_15.dat
rbssim2/resources/stop/2_4_16.dat
rbssim2/resources/stop/2_4_19.dat
rbssim2/resources/stop/2_4_22.dat
rbssim2/resources/stop/2_4_23.dat
rbssim2/resources/stop/2_4_24.dat
rbssim2/resources/stop/2_4_26.dat
rbssim2/resources/stop/2_4_28.dat
rbssim2/resources/stop/2_4_29.dat
rbssim2/resources/stop/2_4_3.dat
rbssim2/resources/stop/2_4_30.dat
rbssim2-0.1.5.dist-info/METADATA
rbssim2-0.1.5.dist-info/WHEEL
rbssim2-0.1.5.dist-info/RECORD
