Metadata-Version: 2.1
Name: rbssim2
Version: 0.1.5
Summary: Backscattering simulation
Author: Timofey Bobrovskiy
Author-email: timofeybobrovskiy@gmail.com
Requires-Python: >=3.8.1,<3.13
Classifier: Programming Language :: Python :: 3
Classifier: Programming Language :: Python :: 3.9
Classifier: Programming Language :: Python :: 3.10
Classifier: Programming Language :: Python :: 3.11
Classifier: Programming Language :: Python :: 3.12
Requires-Dist: mendeleev (>0.1)
Requires-Dist: numba (>=0.58,<0.59)
Requires-Dist: numpy (>=1.22,<1.24)
Requires-Dist: scipy (>=1.9,<1.15)
